{
"type": "FeatureCollection",
"name": "trees",
"crs": { "type": "name", "properties": { "name": "urn:ogc:def:crs:OGC:1.3:CRS84" } },
"features": [
{ "type": "Feature", "properties": { "type": "cherry" }, "geometry": { "type": "Point", "coordinates": [ -84.504931279318029, 38.038316936840587 ] } },
{ "type": "Feature", "properties": { "type": "cherry" }, "geometry": { "type": "Point", "coordinates": [ -84.504998054144039, 38.038468364729127 ] } },
{ "type": "Feature", "properties": { "type": "cherry" }, "geometry": { "type": "Point", "coordinates": [ -84.504674541624979, 38.038404891999598 ] } },
{ "type": "Feature", "properties": { "type": "cherry" }, "geometry": { "type": "Point", "coordinates": [ -84.504578984546427, 38.038315576708442 ] } },
{ "type": "Feature", "properties": { "type": "cherry" }, "geometry": { "type": "Point", "coordinates": [ -84.504435073283503, 38.038355473907806 ] } },
{ "type": "Feature", "properties": { "type": "cherry" }, "geometry": { "type": "Point", "coordinates": [ -84.504468460696501, 38.038395371085421 ] } },
{ "type": "Feature", "properties": { "type": "cherry" }, "geometry": { "type": "Point", "coordinates": [ -84.504562290839928, 38.038480605892076 ] } },
{ "type": "Feature", "properties": { "type": "cherry" }, "geometry": { "type": "Point", "coordinates": [ -84.504581287126641, 38.038516875992485 ] } },
{ "type": "Feature", "properties": { "type": "cherry" }, "geometry": { "type": "Point", "coordinates": [ -84.505069434130448, 38.038408972390997 ] } },
{ "type": "Feature", "properties": { "type": "cherry" }, "geometry": { "type": "Point", "coordinates": [ -84.50509706509294, 38.038621152431062 ] } },
{ "type": "Feature", "properties": { "type": "oak" }, "geometry": { "type": "Point", "coordinates": [ -84.504990570758352, 38.038652888708974 ] } },
{ "type": "Feature", "properties": { "type": "oak" }, "geometry": { "type": "Point", "coordinates": [ -84.504906526580825, 38.038599843779579 ] } },
{ "type": "Feature", "properties": { "type": "oak" }, "geometry": { "type": "Point", "coordinates": [ -84.504816725952765, 38.038632033442184 ] } },
{ "type": "Feature", "properties": { "type": "oak" }, "geometry": { "type": "Point", "coordinates": [ -84.504695840491905, 38.038596216774458 ] } },
{ "type": "Feature", "properties": { "type": "oak" }, "geometry": { "type": "Point", "coordinates": [ -84.50472116887417, 38.038553146074904 ] } },
{ "type": "Feature", "properties": { "type": "oak" }, "geometry": { "type": "Point", "coordinates": [ -84.504713109843451, 38.038485139655592 ] } },
{ "type": "Feature", "properties": { "type": "oak" }, "geometry": { "type": "Point", "coordinates": [ -84.504523722621457, 38.038242129534602 ] } },
{ "type": "Feature", "properties": { "type": "maple" }, "geometry": { "type": "Point", "coordinates": [ -84.505209315877991, 38.038627499687742 ] } },
{ "type": "Feature", "properties": { "type": "maple" }, "geometry": { "type": "Point", "coordinates": [ -84.504949124314649, 38.038253463979807 ] } }
]
}
